{
	"configurations" : 
	[
		{
			"directories" : 
			[
				{
					"build" : ".",
					"childIndexes" : 
					[
						1
					],
					"hasInstallRule" : true,
					"jsonFile" : "directory-.-Release-1418e65d35cd661c8e68.json",
					"minimumCMakeVersion" : 
					{
						"string" : "3.0.2"
					},
					"projectIndex" : 0,
					"source" : ".",
					"targetIndexes" : 
					[
						0,
						1,
						2,
						3,
						4,
						5,
						6,
						7,
						8,
						9,
						10,
						11,
						12,
						17,
						18,
						19,
						20,
						21,
						22,
						23,
						24,
						25,
						26,
						27,
						28,
						29,
						30,
						31,
						32,
						33,
						34,
						35,
						36,
						37,
						38,
						39,
						40,
						41,
						42,
						43,
						44,
						45,
						46,
						47,
						48,
						49,
						50,
						51,
						52,
						53,
						54,
						55
					]
				},
				{
					"build" : "gtest",
					"childIndexes" : 
					[
						2
					],
					"jsonFile" : "directory-gtest-Release-40f9edd0af6c04d6f946.json",
					"minimumCMakeVersion" : 
					{
						"string" : "2.8.8"
					},
					"parentIndex" : 0,
					"projectIndex" : 1,
					"source" : "/usr/src/googletest"
				},
				{
					"build" : "gtest/googlemock",
					"childIndexes" : 
					[
						3
					],
					"jsonFile" : "directory-gtest.googlemock-Release-8fd0af86403c015b5fbc.json",
					"minimumCMakeVersion" : 
					{
						"string" : "2.6.4"
					},
					"parentIndex" : 1,
					"projectIndex" : 2,
					"source" : "/usr/src/googletest/googlemock",
					"targetIndexes" : 
					[
						13,
						14
					]
				},
				{
					"build" : "gtest/googletest",
					"jsonFile" : "directory-gtest.googletest-Release-5804ba12edef54b53d36.json",
					"minimumCMakeVersion" : 
					{
						"string" : "2.6.4"
					},
					"parentIndex" : 2,
					"projectIndex" : 3,
					"source" : "/usr/src/googletest/googletest",
					"targetIndexes" : 
					[
						15,
						16
					]
				}
			],
			"name" : "Release",
			"projects" : 
			[
				{
					"childIndexes" : 
					[
						1
					],
					"directoryIndexes" : 
					[
						0
					],
					"name" : "uneven_map",
					"targetIndexes" : 
					[
						0,
						1,
						2,
						3,
						4,
						5,
						6,
						7,
						8,
						9,
						10,
						11,
						12,
						17,
						18,
						19,
						20,
						21,
						22,
						23,
						24,
						25,
						26,
						27,
						28,
						29,
						30,
						31,
						32,
						33,
						34,
						35,
						36,
						37,
						38,
						39,
						40,
						41,
						42,
						43,
						44,
						45,
						46,
						47,
						48,
						49,
						50,
						51,
						52,
						53,
						54,
						55
					]
				},
				{
					"childIndexes" : 
					[
						2
					],
					"directoryIndexes" : 
					[
						1
					],
					"name" : "googletest-distribution",
					"parentIndex" : 0
				},
				{
					"childIndexes" : 
					[
						3
					],
					"directoryIndexes" : 
					[
						2
					],
					"name" : "gmock",
					"parentIndex" : 1,
					"targetIndexes" : 
					[
						13,
						14
					]
				},
				{
					"directoryIndexes" : 
					[
						3
					],
					"name" : "gtest",
					"parentIndex" : 2,
					"targetIndexes" : 
					[
						15,
						16
					]
				}
			],
			"targets" : 
			[
				{
					"directoryIndex" : 0,
					"id" : "actionlib_msgs_generate_messages_cpp::@6890427a1f51a3e7e1df",
					"jsonFile" : "target-actionlib_msgs_generate_messages_cpp-Release-0b5227f47db2ade28ac6.json",
					"name" : "actionlib_msgs_generate_messages_cpp",
					"projectIndex" : 0
				},
				{
					"directoryIndex" : 0,
					"id" : "actionlib_msgs_generate_messages_eus::@6890427a1f51a3e7e1df",
					"jsonFile" : "target-actionlib_msgs_generate_messages_eus-Release-0d4d2cb451b5e15ca06a.json",
					"name" : "actionlib_msgs_generate_messages_eus",
					"projectIndex" : 0
				},
				{
					"directoryIndex" : 0,
					"id" : "actionlib_msgs_generate_messages_lisp::@6890427a1f51a3e7e1df",
					"jsonFile" : "target-actionlib_msgs_generate_messages_lisp-Release-c02334fc820ba9bc0927.json",
					"name" : "actionlib_msgs_generate_messages_lisp",
					"projectIndex" : 0
				},
				{
					"directoryIndex" : 0,
					"id" : "actionlib_msgs_generate_messages_nodejs::@6890427a1f51a3e7e1df",
					"jsonFile" : "target-actionlib_msgs_generate_messages_nodejs-Release-39baf184fa165e6b01cf.json",
					"name" : "actionlib_msgs_generate_messages_nodejs",
					"projectIndex" : 0
				},
				{
					"directoryIndex" : 0,
					"id" : "actionlib_msgs_generate_messages_py::@6890427a1f51a3e7e1df",
					"jsonFile" : "target-actionlib_msgs_generate_messages_py-Release-f86606cf39895a7ea00e.json",
					"name" : "actionlib_msgs_generate_messages_py",
					"projectIndex" : 0
				},
				{
					"directoryIndex" : 0,
					"id" : "clean_test_results::@6890427a1f51a3e7e1df",
					"jsonFile" : "target-clean_test_results-Release-16e9a37958255a19a306.json",
					"name" : "clean_test_results",
					"projectIndex" : 0
				},
				{
					"directoryIndex" : 0,
					"id" : "download_extra_data::@6890427a1f51a3e7e1df",
					"jsonFile" : "target-download_extra_data-Release-6efb863ed2e55ebfbeab.json",
					"name" : "download_extra_data",
					"projectIndex" : 0
				},
				{
					"directoryIndex" : 0,
					"id" : "doxygen::@6890427a1f51a3e7e1df",
					"jsonFile" : "target-doxygen-Release-6b85fb5bd8bdcb634c30.json",
					"name" : "doxygen",
					"projectIndex" : 0
				},
				{
					"directoryIndex" : 0,
					"id" : "geometry_msgs_generate_messages_cpp::@6890427a1f51a3e7e1df",
					"jsonFile" : "target-geometry_msgs_generate_messages_cpp-Release-05a2f28fb1b678920568.json",
					"name" : "geometry_msgs_generate_messages_cpp",
					"projectIndex" : 0
				},
				{
					"directoryIndex" : 0,
					"id" : "geometry_msgs_generate_messages_eus::@6890427a1f51a3e7e1df",
					"jsonFile" : "target-geometry_msgs_generate_messages_eus-Release-ebe4b7215178274e12f5.json",
					"name" : "geometry_msgs_generate_messages_eus",
					"projectIndex" : 0
				},
				{
					"directoryIndex" : 0,
					"id" : "geometry_msgs_generate_messages_lisp::@6890427a1f51a3e7e1df",
					"jsonFile" : "target-geometry_msgs_generate_messages_lisp-Release-d407347282ae05e9ce96.json",
					"name" : "geometry_msgs_generate_messages_lisp",
					"projectIndex" : 0
				},
				{
					"directoryIndex" : 0,
					"id" : "geometry_msgs_generate_messages_nodejs::@6890427a1f51a3e7e1df",
					"jsonFile" : "target-geometry_msgs_generate_messages_nodejs-Release-0de71cf3ece1f80fef90.json",
					"name" : "geometry_msgs_generate_messages_nodejs",
					"projectIndex" : 0
				},
				{
					"directoryIndex" : 0,
					"id" : "geometry_msgs_generate_messages_py::@6890427a1f51a3e7e1df",
					"jsonFile" : "target-geometry_msgs_generate_messages_py-Release-6f1516a0da6581419e16.json",
					"name" : "geometry_msgs_generate_messages_py",
					"projectIndex" : 0
				},
				{
					"directoryIndex" : 2,
					"id" : "gmock::@e3f94eedc5dc07131386",
					"jsonFile" : "target-gmock-Release-c57d6fca792fed5e4e7c.json",
					"name" : "gmock",
					"projectIndex" : 2
				},
				{
					"directoryIndex" : 2,
					"id" : "gmock_main::@e3f94eedc5dc07131386",
					"jsonFile" : "target-gmock_main-Release-b8afd793e1f59d7f37fd.json",
					"name" : "gmock_main",
					"projectIndex" : 2
				},
				{
					"directoryIndex" : 3,
					"id" : "gtest::@b738d542747fbb7ea6e3",
					"jsonFile" : "target-gtest-Release-455c739af1d00d1880af.json",
					"name" : "gtest",
					"projectIndex" : 3
				},
				{
					"directoryIndex" : 3,
					"id" : "gtest_main::@b738d542747fbb7ea6e3",
					"jsonFile" : "target-gtest_main-Release-65e30dc55984c6673af2.json",
					"name" : "gtest_main",
					"projectIndex" : 3
				},
				{
					"directoryIndex" : 0,
					"id" : "nav_msgs_generate_messages_cpp::@6890427a1f51a3e7e1df",
					"jsonFile" : "target-nav_msgs_generate_messages_cpp-Release-f7655c1acf65ce7e96bc.json",
					"name" : "nav_msgs_generate_messages_cpp",
					"projectIndex" : 0
				},
				{
					"directoryIndex" : 0,
					"id" : "nav_msgs_generate_messages_eus::@6890427a1f51a3e7e1df",
					"jsonFile" : "target-nav_msgs_generate_messages_eus-Release-5d72f441ee579c00f0d2.json",
					"name" : "nav_msgs_generate_messages_eus",
					"projectIndex" : 0
				},
				{
					"directoryIndex" : 0,
					"id" : "nav_msgs_generate_messages_lisp::@6890427a1f51a3e7e1df",
					"jsonFile" : "target-nav_msgs_generate_messages_lisp-Release-cc6436feae6d8b2d5eda.json",
					"name" : "nav_msgs_generate_messages_lisp",
					"projectIndex" : 0
				},
				{
					"directoryIndex" : 0,
					"id" : "nav_msgs_generate_messages_nodejs::@6890427a1f51a3e7e1df",
					"jsonFile" : "target-nav_msgs_generate_messages_nodejs-Release-8be608a3e265dd243376.json",
					"name" : "nav_msgs_generate_messages_nodejs",
					"projectIndex" : 0
				},
				{
					"directoryIndex" : 0,
					"id" : "nav_msgs_generate_messages_py::@6890427a1f51a3e7e1df",
					"jsonFile" : "target-nav_msgs_generate_messages_py-Release-c22ecb754eab3d10c1f3.json",
					"name" : "nav_msgs_generate_messages_py",
					"projectIndex" : 0
				},
				{
					"directoryIndex" : 0,
					"id" : "pcl_msgs_generate_messages_cpp::@6890427a1f51a3e7e1df",
					"jsonFile" : "target-pcl_msgs_generate_messages_cpp-Release-5dc058ea2953a6cd6858.json",
					"name" : "pcl_msgs_generate_messages_cpp",
					"projectIndex" : 0
				},
				{
					"directoryIndex" : 0,
					"id" : "pcl_msgs_generate_messages_eus::@6890427a1f51a3e7e1df",
					"jsonFile" : "target-pcl_msgs_generate_messages_eus-Release-c0fcbe1e48b0dfaea7f2.json",
					"name" : "pcl_msgs_generate_messages_eus",
					"projectIndex" : 0
				},
				{
					"directoryIndex" : 0,
					"id" : "pcl_msgs_generate_messages_lisp::@6890427a1f51a3e7e1df",
					"jsonFile" : "target-pcl_msgs_generate_messages_lisp-Release-b14c3f3aef3140d4e26b.json",
					"name" : "pcl_msgs_generate_messages_lisp",
					"projectIndex" : 0
				},
				{
					"directoryIndex" : 0,
					"id" : "pcl_msgs_generate_messages_nodejs::@6890427a1f51a3e7e1df",
					"jsonFile" : "target-pcl_msgs_generate_messages_nodejs-Release-55cc9a2cb8d384b9bf0e.json",
					"name" : "pcl_msgs_generate_messages_nodejs",
					"projectIndex" : 0
				},
				{
					"directoryIndex" : 0,
					"id" : "pcl_msgs_generate_messages_py::@6890427a1f51a3e7e1df",
					"jsonFile" : "target-pcl_msgs_generate_messages_py-Release-12462d9fc318c3eadac9.json",
					"name" : "pcl_msgs_generate_messages_py",
					"projectIndex" : 0
				},
				{
					"directoryIndex" : 0,
					"id" : "roscpp_generate_messages_cpp::@6890427a1f51a3e7e1df",
					"jsonFile" : "target-roscpp_generate_messages_cpp-Release-969d7c0063357e4d9233.json",
					"name" : "roscpp_generate_messages_cpp",
					"projectIndex" : 0
				},
				{
					"directoryIndex" : 0,
					"id" : "roscpp_generate_messages_eus::@6890427a1f51a3e7e1df",
					"jsonFile" : "target-roscpp_generate_messages_eus-Release-927c37a70a9202366ee1.json",
					"name" : "roscpp_generate_messages_eus",
					"projectIndex" : 0
				},
				{
					"directoryIndex" : 0,
					"id" : "roscpp_generate_messages_lisp::@6890427a1f51a3e7e1df",
					"jsonFile" : "target-roscpp_generate_messages_lisp-Release-46dee1958d4cb50842ce.json",
					"name" : "roscpp_generate_messages_lisp",
					"projectIndex" : 0
				},
				{
					"directoryIndex" : 0,
					"id" : "roscpp_generate_messages_nodejs::@6890427a1f51a3e7e1df",
					"jsonFile" : "target-roscpp_generate_messages_nodejs-Release-4c44f13efea915d40720.json",
					"name" : "roscpp_generate_messages_nodejs",
					"projectIndex" : 0
				},
				{
					"directoryIndex" : 0,
					"id" : "roscpp_generate_messages_py::@6890427a1f51a3e7e1df",
					"jsonFile" : "target-roscpp_generate_messages_py-Release-bd2bbe14bf26a81c1ae9.json",
					"name" : "roscpp_generate_messages_py",
					"projectIndex" : 0
				},
				{
					"directoryIndex" : 0,
					"id" : "rosgraph_msgs_generate_messages_cpp::@6890427a1f51a3e7e1df",
					"jsonFile" : "target-rosgraph_msgs_generate_messages_cpp-Release-52668326c96f47566451.json",
					"name" : "rosgraph_msgs_generate_messages_cpp",
					"projectIndex" : 0
				},
				{
					"directoryIndex" : 0,
					"id" : "rosgraph_msgs_generate_messages_eus::@6890427a1f51a3e7e1df",
					"jsonFile" : "target-rosgraph_msgs_generate_messages_eus-Release-7fdd0ae8292e2e7f8d56.json",
					"name" : "rosgraph_msgs_generate_messages_eus",
					"projectIndex" : 0
				},
				{
					"directoryIndex" : 0,
					"id" : "rosgraph_msgs_generate_messages_lisp::@6890427a1f51a3e7e1df",
					"jsonFile" : "target-rosgraph_msgs_generate_messages_lisp-Release-30cab1635642315a8ad4.json",
					"name" : "rosgraph_msgs_generate_messages_lisp",
					"projectIndex" : 0
				},
				{
					"directoryIndex" : 0,
					"id" : "rosgraph_msgs_generate_messages_nodejs::@6890427a1f51a3e7e1df",
					"jsonFile" : "target-rosgraph_msgs_generate_messages_nodejs-Release-d20807c312c4f0ad6295.json",
					"name" : "rosgraph_msgs_generate_messages_nodejs",
					"projectIndex" : 0
				},
				{
					"directoryIndex" : 0,
					"id" : "rosgraph_msgs_generate_messages_py::@6890427a1f51a3e7e1df",
					"jsonFile" : "target-rosgraph_msgs_generate_messages_py-Release-aaef8203fd976a12ac23.json",
					"name" : "rosgraph_msgs_generate_messages_py",
					"projectIndex" : 0
				},
				{
					"directoryIndex" : 0,
					"id" : "run_tests::@6890427a1f51a3e7e1df",
					"jsonFile" : "target-run_tests-Release-fc514321a1b4d4af8cfc.json",
					"name" : "run_tests",
					"projectIndex" : 0
				},
				{
					"directoryIndex" : 0,
					"id" : "sensor_msgs_generate_messages_cpp::@6890427a1f51a3e7e1df",
					"jsonFile" : "target-sensor_msgs_generate_messages_cpp-Release-6fce9f912630503a62d9.json",
					"name" : "sensor_msgs_generate_messages_cpp",
					"projectIndex" : 0
				},
				{
					"directoryIndex" : 0,
					"id" : "sensor_msgs_generate_messages_eus::@6890427a1f51a3e7e1df",
					"jsonFile" : "target-sensor_msgs_generate_messages_eus-Release-b0d41035e1e17d4daa0b.json",
					"name" : "sensor_msgs_generate_messages_eus",
					"projectIndex" : 0
				},
				{
					"directoryIndex" : 0,
					"id" : "sensor_msgs_generate_messages_lisp::@6890427a1f51a3e7e1df",
					"jsonFile" : "target-sensor_msgs_generate_messages_lisp-Release-c0f1936a1fc99be7ff3d.json",
					"name" : "sensor_msgs_generate_messages_lisp",
					"projectIndex" : 0
				},
				{
					"directoryIndex" : 0,
					"id" : "sensor_msgs_generate_messages_nodejs::@6890427a1f51a3e7e1df",
					"jsonFile" : "target-sensor_msgs_generate_messages_nodejs-Release-f75c0fc03d8da7739eb3.json",
					"name" : "sensor_msgs_generate_messages_nodejs",
					"projectIndex" : 0
				},
				{
					"directoryIndex" : 0,
					"id" : "sensor_msgs_generate_messages_py::@6890427a1f51a3e7e1df",
					"jsonFile" : "target-sensor_msgs_generate_messages_py-Release-2ec5bf0b4e20c32b0b9c.json",
					"name" : "sensor_msgs_generate_messages_py",
					"projectIndex" : 0
				},
				{
					"directoryIndex" : 0,
					"id" : "std_msgs_generate_messages_cpp::@6890427a1f51a3e7e1df",
					"jsonFile" : "target-std_msgs_generate_messages_cpp-Release-ba1e7d500ddb7a78877f.json",
					"name" : "std_msgs_generate_messages_cpp",
					"projectIndex" : 0
				},
				{
					"directoryIndex" : 0,
					"id" : "std_msgs_generate_messages_eus::@6890427a1f51a3e7e1df",
					"jsonFile" : "target-std_msgs_generate_messages_eus-Release-0cd867ead53d6a3319ff.json",
					"name" : "std_msgs_generate_messages_eus",
					"projectIndex" : 0
				},
				{
					"directoryIndex" : 0,
					"id" : "std_msgs_generate_messages_lisp::@6890427a1f51a3e7e1df",
					"jsonFile" : "target-std_msgs_generate_messages_lisp-Release-58b027db542112ebc449.json",
					"name" : "std_msgs_generate_messages_lisp",
					"projectIndex" : 0
				},
				{
					"directoryIndex" : 0,
					"id" : "std_msgs_generate_messages_nodejs::@6890427a1f51a3e7e1df",
					"jsonFile" : "target-std_msgs_generate_messages_nodejs-Release-cf6a1a3c9d767279b517.json",
					"name" : "std_msgs_generate_messages_nodejs",
					"projectIndex" : 0
				},
				{
					"directoryIndex" : 0,
					"id" : "std_msgs_generate_messages_py::@6890427a1f51a3e7e1df",
					"jsonFile" : "target-std_msgs_generate_messages_py-Release-c011b29da31fcfc3a651.json",
					"name" : "std_msgs_generate_messages_py",
					"projectIndex" : 0
				},
				{
					"directoryIndex" : 0,
					"id" : "tests::@6890427a1f51a3e7e1df",
					"jsonFile" : "target-tests-Release-5d5369c97d73a46ddf48.json",
					"name" : "tests",
					"projectIndex" : 0
				},
				{
					"directoryIndex" : 0,
					"id" : "uneven_map::@6890427a1f51a3e7e1df",
					"jsonFile" : "target-uneven_map-Release-f82562107e8e9e2b1446.json",
					"name" : "uneven_map",
					"projectIndex" : 0
				},
				{
					"directoryIndex" : 0,
					"id" : "uneven_map_node::@6890427a1f51a3e7e1df",
					"jsonFile" : "target-uneven_map_node-Release-94bb261fa7cab112a76e.json",
					"name" : "uneven_map_node",
					"projectIndex" : 0
				},
				{
					"directoryIndex" : 0,
					"id" : "visualization_msgs_generate_messages_cpp::@6890427a1f51a3e7e1df",
					"jsonFile" : "target-visualization_msgs_generate_messages_cpp-Release-ae539bc7848de916d709.json",
					"name" : "visualization_msgs_generate_messages_cpp",
					"projectIndex" : 0
				},
				{
					"directoryIndex" : 0,
					"id" : "visualization_msgs_generate_messages_eus::@6890427a1f51a3e7e1df",
					"jsonFile" : "target-visualization_msgs_generate_messages_eus-Release-70c20cf44dd2220e325f.json",
					"name" : "visualization_msgs_generate_messages_eus",
					"projectIndex" : 0
				},
				{
					"directoryIndex" : 0,
					"id" : "visualization_msgs_generate_messages_lisp::@6890427a1f51a3e7e1df",
					"jsonFile" : "target-visualization_msgs_generate_messages_lisp-Release-2e6bd85849c976e37dc9.json",
					"name" : "visualization_msgs_generate_messages_lisp",
					"projectIndex" : 0
				},
				{
					"directoryIndex" : 0,
					"id" : "visualization_msgs_generate_messages_nodejs::@6890427a1f51a3e7e1df",
					"jsonFile" : "target-visualization_msgs_generate_messages_nodejs-Release-c29c1e40544ab7f5d7df.json",
					"name" : "visualization_msgs_generate_messages_nodejs",
					"projectIndex" : 0
				},
				{
					"directoryIndex" : 0,
					"id" : "visualization_msgs_generate_messages_py::@6890427a1f51a3e7e1df",
					"jsonFile" : "target-visualization_msgs_generate_messages_py-Release-2c8df9bbb52e0c09cb01.json",
					"name" : "visualization_msgs_generate_messages_py",
					"projectIndex" : 0
				}
			]
		}
	],
	"kind" : "codemodel",
	"paths" : 
	{
		"build" : "/home/yzh/\u5bfc\u822a\u6846\u67b6/uneven_planner/src/uneven_planner/uneven_map/cmake-build-debug",
		"source" : "/home/yzh/\u5bfc\u822a\u6846\u67b6/uneven_planner/src/uneven_planner/uneven_map"
	},
	"version" : 
	{
		"major" : 2,
		"minor" : 5
	}
}
